texttoolspy/__init__.py
texttoolspy/main.py
texttoolspy-1.0.0.dist-info/Licence.txt
texttoolspy-1.0.0.dist-info/METADATA
texttoolspy-1.0.0.dist-info/WHEEL
texttoolspy-1.0.0.dist-info/top_level.txt
texttoolspy-1.0.0.dist-info/RECORD
