Metadata-Version: 2.1
Name: texttoolspy
Version: 1.0.0
Summary: A tool that allows you to create responsive tools in text
Author: MilesWK
Author-email: your_name@example.com
License: MIT
Classifier: Programming Language :: Python :: 3
Classifier: License :: OSI Approved :: MIT License
Classifier: Operating System :: OS Independent
Classifier: Development Status :: 5 - Production/Stable
License-File: Licence.txt
Requires-Dist: termcolor
Requires-Dist: colorama
Requires-Dist: readchar
Requires-Dist: cursor
